LICENSE.txt
MANIFEST.in
README.md
setup.cfg
setup.py
django_navsy.egg-info/PKG-INFO
django_navsy.egg-info/SOURCES.txt
django_navsy.egg-info/dependency_links.txt
django_navsy.egg-info/requires.txt
django_navsy.egg-info/top_level.txt
navsy/TODO.txt
navsy/__init__.py
navsy/admin.py
navsy/apps.py
navsy/cache.py
navsy/context_processors.py
navsy/exceptions.py
navsy/forms.py
navsy/models.py
navsy/settings.py
navsy/signals.py
navsy/sitemaps.py
navsy/translation.py
navsy/urls.py
navsy/version.py
navsy/views.py
navsy/migrations/0001_initial.py
navsy/migrations/0002_route_published.py
navsy/migrations/0003_page_sitemap.py
navsy/migrations/0004_page_seo.py
navsy/migrations/0005_page_slug_unique_with_parent.py
navsy/migrations/0006_removed_slug_uniqueness.py
navsy/migrations/0007_added_treenode.py
navsy/migrations/0008_removed_autoslugfield.py
navsy/migrations/0009_updated_treenode_level_default.py
navsy/migrations/0010_added_regex_fields_to_route.py
navsy/migrations/0011_removed_pattern_model.py
navsy/migrations/0012_removed_regex_extra_fields.py
navsy/migrations/0013_remove_route_redirect_to_first_child_page.py
navsy/migrations/0014_page_status.py
navsy/migrations/0015_fixed_route_default_ordering.py
navsy/migrations/0016_remove_page_published.py
navsy/migrations/0017_renamed_page_route_fields_with_is_prefix.py
navsy/migrations/0018_fixed_route_default_ordering.py
navsy/migrations/__init__.py
navsy/static/navsy/css/default.css
navsy/templates/navsy/breadcrumbs.html
navsy/templates/navsy/default.html
navsy/templates/navsy/languages-alternate-href.html
navsy/templates/navsy/languages-menu.html
navsy/templates/navsy/menu.html
navsy/templates/navsy/pagination.html
navsy/templatetags/__init__.py
navsy/templatetags/navsy_tags.py
navsy/utils/__init__.py
navsy/utils/i18n_utils.py
navsy/utils/path_utils.py
navsy/utils/pattern_utils.py
navsy/utils/url_utils.py