Metadata-Version: 1.1
Name: django-navsy
Version: 0.5.3
Summary: django-navsy is a fast navigation system for lazy devs.
Home-page: https://github.com/fabiocaccamo/django-navsy
Author: Fabio Caccamo
Author-email: fabio.caccamo@gmail.com
License: MIT
Download-URL: https://github.com/fabiocaccamo/django-navsy/archive/0.5.3.tar.gz
Keywords: django,navigation,nav,system,controller,router,routes,urls,pages,menu,breadcrumbs,tree,fast
Platform: UNKNOWN
Classifier: Development Status :: 5 - Production/Stable
Classifier: Environment :: Web Environment
Classifier: Framework :: Django
Classifier: Framework :: Django :: 1.8
Classifier: Framework :: Django :: 1.9
Classifier: Framework :: Django :: 1.10
Classifier: Framework :: Django :: 1.11
Classifier: Framework :: Django :: 2.0
Classifier: Intended Audience :: Developers
Classifier: License :: OSI Approved :: MIT License
Classifier: Natural Language :: English
Classifier: Operating System :: OS Independent
Classifier: Programming Language :: Python :: 2
Classifier: Programming Language :: Python :: 2.7
Classifier: Programming Language :: Python :: 3
Classifier: Programming Language :: Python :: 3.4
Classifier: Programming Language :: Python :: 3.5
Classifier: Programming Language :: Python :: 3.6
Classifier: Topic :: Software Development :: Build Tools
Requires: django(>=1.8)
